sitemapr/__init__.py
sitemapr/core.py
sitemapr/models.py
sitemapr/py.typed
sitemapr-0.3.3.dist-info/LICENSE
sitemapr-0.3.3.dist-info/METADATA
sitemapr-0.3.3.dist-info/WHEEL
sitemapr-0.3.3.dist-info/RECORD
