Metadata-Version: 2.3
Name: sitemapr
Version: 0.3.3
Summary: sitemapr is a library that generates sitemaps for SPA websites with declaritve configuration in Python.
License: MIT
Author: sjquant
Author-email: seonujang92@gmail.com
Requires-Python: >=3.10,<4.0
Classifier: License :: OSI Approved :: MIT License
Classifier: Programming Language :: Python :: 3
Classifier: Programming Language :: Python :: 3.10
Classifier: Programming Language :: Python :: 3.11
Classifier: Programming Language :: Python :: 3.12
Classifier: Programming Language :: Python :: 3.13
Requires-Dist: pydantic (>=2.6.3,<3.0.0)
